{
  "frames": {
    "puzzle-bg-2": {
      "frame": {
        "x": 2,
        "y": 2,
        "w": 667,
        "h": 1000
      },
      "rotated": false,
      "trimmed": false,
      "spriteSourceSize": {
        "x": 0,
        "y": 0,
        "w": 667,
        "h": 1000
      },
      "sourceSize": {
        "w": 667,
        "h": 1000
      }
    },
    "puzzle-bg-1": {
      "frame": {
        "x": 671,
        "y": 2,
        "w": 1130,
        "h": 921
      },
      "rotated": true,
      "trimmed": false,
      "spriteSourceSize": {
        "x": 0,
        "y": 0,
        "w": 1130,
        "h": 921
      },
      "sourceSize": {
        "w": 1130,
        "h": 921
      }
    },
    "cloud-overlay": {
      "frame": {
        "x": 2,
        "y": 1134,
        "w": 147,
        "h": 150
      },
      "rotated": true,
      "trimmed": false,
      "spriteSourceSize": {
        "x": 0,
        "y": 0,
        "w": 147,
        "h": 150
      },
      "sourceSize": {
        "w": 147,
        "h": 150
      }
    },
    "cloud-3": {
      "frame": {
        "x": 154,
        "y": 1004,
        "w": 402,
        "h": 179
      },
      "rotated": false,
      "trimmed": true,
      "spriteSourceSize": {
        "x": 0,
        "y": 0,
        "w": 402,
        "h": 179
      },
      "sourceSize": {
        "w": 402,
        "h": 180
      }
    },
    "cloud-2": {
      "frame": {
        "x": 2,
        "y": 1283,
        "w": 305,
        "h": 162
      },
      "rotated": false,
      "trimmed": false,
      "spriteSourceSize": {
        "x": 0,
        "y": 0,
        "w": 305,
        "h": 162
      },
      "sourceSize": {
        "w": 305,
        "h": 162
      }
    },
    "cloud-1": {
      "frame": {
        "x": 309,
        "y": 1185,
        "w": 319,
        "h": 186
      },
      "rotated": false,
      "trimmed": false,
      "spriteSourceSize": {
        "x": 0,
        "y": 0,
        "w": 319,
        "h": 186
      },
      "sourceSize": {
        "w": 319,
        "h": 186
      }
    }
  },
  "meta": {
    "app": "http://github.com/pixijs/assetpack",
    "version": "1.0",
    "image": "backgrounds.webp",
    "format": "RGBA8888",
    "size": {
      "w": 1594,
      "h": 1447
    },
    "scale": 1,
    "related_multi_packs": []
  }
}